{
  "title": "Do Lox and Other Smoked Fish Increase Cancer Risk?",
  "link": "https://www.nytimes.com/2019/07/26/well/eat/does-lox-and-other-smoked-fish-increase-cancer-risk.html",
  "guid": "https://www.nytimes.com/2019/07/26/well/eat/does-lox-and-other-smoked-fish-increase-cancer-risk.html",
  "atom:link": "",
  "description": "From a cancer risk perspective, the American Institute for Cancer Research considers smoked and cured fish in the same category as processed meats.",
  "dc:creator": "Sophie Egan",
  "pubDate": "Fri, 26 Jul 2019 11:27:52 +0000",
  "category": [
    "Meat",
    "Seafood",
    "Fish and Other Marine Life",
    "Hazardous and Toxic Substances",
    "Colon and Colorectal Cancer",
    "Cancer"
  ],
  "media:content": "",
  "media:credit": "Erica Yoon for The New York Times"
}