{
  "title": "Ronald Lauder: New York’s Billionaire Political Disrupter",
  "link": "https://www.nytimes.com/2022/11/06/nyregion/ronald-lauder-zeldin-governor.html",
  "guid": "https://www.nytimes.com/2022/11/06/nyregion/ronald-lauder-zeldin-governor.html",
  "atom:link": "",
  "description": "The cosmetics heir has pumped at least $11 million into efforts to elect Representative Lee Zeldin, a Republican, as governor of New York.",
  "dc:creator": "Nicholas Fandos and Dana Rubinstein",
  "pubDate": "Sun, 06 Nov 2022 08:00:20 +0000",
  "category": [
    "Lauder, Ronald S",
    "Zeldin, Lee M",
    "Midterm Elections (2022)",
    "High Net Worth Individuals",
    "Politics and Government",
    "Campaign Finance",
    "Elections, Governors",
    "Content Type: Personal Profile",
    "Term Limits (Political Office)",
    "New York State",
    "Estee Lauder Companies Inc",
    "Republican Party",
    "Hochul, Kathleen C"
  ],
  "media:content": "",
  "media:credit": "Carly Zavala for The New York Times",
  "media:description": "Ronald S. Lauder has thrown millions of dollars behind conservative causes in New York."
}