{
  "title": "2 Newark Police Officers Shot by Gunman on Rooftop, Officials Say",
  "link": "https://www.nytimes.com/2022/11/01/nyregion/newark-nj-police-shooting.html",
  "guid": "https://www.nytimes.com/2022/11/01/nyregion/newark-nj-police-shooting.html",
  "atom:link": "",
  "description": "One officer was shot in the shoulder and the other one was shot in the leg by a person firing a long gun, according to law enforcement officials.",
  "dc:creator": "Liam Stack, Tracey Tully and Sarah Maslin Nir",
  "pubDate": "Tue, 01 Nov 2022 21:06:54 +0000",
  "category": [
    "Attacks on Police",
    "Newark (NJ)"
  ],
  "media:content": "",
  "media:credit": "Bryan Anselm for The New York Times",
  "media:description": "The police blocked off an intersection in Newark, N.J., on Tuesday afternoon following a reported shooting."
}