{
  "title": "Thanksgiving Salads and Desserts Beyond Pie",
  "link": "https://www.nytimes.com/2022/11/11/dining/thanksgiving-salads-and-desserts-beyond-pie.html",
  "guid": "https://www.nytimes.com/2022/11/11/dining/thanksgiving-salads-and-desserts-beyond-pie.html",
  "atom:link": "",
  "description": "Planning continues with new recipes from Yewande Komolafe and Melissa Clark, and wine guidance from Eric Asimov.",
  "dc:creator": "Sam Sifton",
  "pubDate": "Fri, 11 Nov 2022 16:00:04 +0000",
  "category": [
    "Cooking and Cookbooks",
    "Content Type: Service"
  ],
  "media:content": {
    "media:credit": "Armando Rafael for The New York Times"
  }
}