{
  "title": "¿Quién ganará la batalla por el Congreso?",
  "link": "https://www.nytimes.com/es/2022/11/07/espanol/quien-ganara-congreso-usa.html",
  "guid": "https://www.nytimes.com/es/2022/11/07/espanol/quien-ganara-congreso-usa.html",
  "atom:link": "",
  "description": "En las elecciones de mitad de mandato de EE. UU. casi todo es posible. Estos son cuatro escenarios probables.",
  "dc:creator": "Nate Cohn",
  "pubDate": "Mon, 07 Nov 2022 20:02:20 +0000",
  "category": [
    "Midterm Elections (2022)",
    "United States Politics and Government",
    "internal-sub-only-nl",
    "Polls and Public Opinion",
    "Elections, Senate",
    "Presidential Election of 2020",
    "Elections, House of Representatives"
  ]
}