{
  "title": "After Win, Hochul Confronts Challenges and Some Second-Guessing",
  "link": "https://www.nytimes.com/2022/11/09/nyregion/kathy-hochul-governor.html",
  "guid": "https://www.nytimes.com/2022/11/09/nyregion/kathy-hochul-governor.html",
  "atom:link": "",
  "description": "Gov. Kathy Hochul managed to repel late momentum by her Republican opponent, Lee Zeldin. Now she must govern over a fractured New York electorate.",
  "dc:creator": "Luis Ferré-Sadurní",
  "pubDate": "Wed, 09 Nov 2022 13:36:58 +0000",
  "category": [
    "Hochul, Kathleen C",
    "Midterm Elections (2022)",
    "Elections, Governors",
    "Politics and Government",
    "Women and Girls",
    "Governors (US)",
    "Records and Achievements",
    "Content Type: Personal Profile",
    "New York State",
    "Democratic Party"
  ],
  "media:content": "",
  "media:credit": "Hiroko Masuike/The New York Times",
  "media:description": "Gov. Kathy Hochul on Tuesday became the first woman to be elected governor of New York."
}