{
  "title": "Malaysia Unemployed Persons",
  "link": "https://tradingeconomics.com/malaysia/unemployed-persons",
  "description": "The number of unemployed persons in Malaysia decreased to 605 Thousand in September of 2022 from 612 Thousand in August of 2022. Unemployed Persons in Malaysia averaged 484.52 Thousand from 1985 until 2022, reaching an all time high of 826.10 Thousand in May of 2020 and a record low of 210.50 Thousand in December of 1996. In Malaysia, unemployed persons are individuals who are without a job and actively seeking to work. This page provides - Malaysia Unemployed Persons - actual values, historical data, forecast, chart, statistics, economic calendar and news.",
  "author": "Department of Statistics, Malaysia",
  "pubDate": "Tue, 08 Nov 2022 04:45:35 GMT"
}