{
  "title": "How Europe Is Reacting to the US Midterm Elections",
  "link": "https://www.nytimes.com/2022/11/10/world/europe/europe-republican-party-election-ukraine.html",
  "guid": "https://www.nytimes.com/2022/11/10/world/europe/europe-republican-party-election-ukraine.html",
  "atom:link": "",
  "description": "With the MAGA star dimmed, analysts expect continued support in Washington for Ukraine and NATO, and perhaps greater pressure on China.",
  "dc:creator": "Steven Erlanger and Alexandra Stevenson",
  "pubDate": "Thu, 10 Nov 2022 23:23:47 +0000",
  "category": [
    "Midterm Elections (2022)",
    "Republican Party",
    "Democratic Party",
    "House of Representatives",
    "Biden, Joseph R Jr",
    "McCarthy, Kevin (1965- )",
    "Trump, Donald J",
    "Europe",
    "Taiwan",
    "Ukraine",
    "Xinjiang (China)",
    "North Atlantic Treaty Organization"
  ],
  "media:content": "",
  "media:credit": "T.J. Kirkpatrick for The New York Times",
  "media:description": "The U.S. Capitol in Washington after Election Day. The shape of the next Congress is still unsettled, but reactions from abroad were already coming in."
}