{
  "title": "Japan Household Spending YoY",
  "link": "https://tradingeconomics.com/japan/household-spending",
  "description": "Household Spending in Japan increased 2.30 percent in September of 2022 over the previous month. Household Spending in Japan averaged -0.69 percent from 2001 until 2022, reaching an all time high of 13 percent in April of 2021 and a record low of -16.20 percent in May of 2020. In Japan, Household Spending YoY refers to the annual change of consumption expenditures (on food, housing, utilities, furniture, clothing, health, education, transport, communication, leisure activities, etc.) in real terms for two-or-more-person households including agricultural, forestry and fisheries households. This page provides the latest reported value for - Japan Household Spending - plus previous releases, historical high and low, short-term forecast and long-term prediction, economic calendar, survey consensus and news.",
  "author": "Ministry of Internal Affairs & Communications",
  "pubDate": "Tue, 08 Nov 2022 00:15:55 GMT"
}