{
  "title": "Trump Asks Supreme Court to Block the House From Obtaining His Tax Returns",
  "link": "https://www.nytimes.com/2022/10/31/us/politics/trump-tax-returns-supreme-court.html",
  "guid": "https://www.nytimes.com/2022/10/31/us/politics/trump-tax-returns-supreme-court.html",
  "atom:link": "",
  "description": "The request would further delay a long-running request by the House Ways and Means Committee as the midterm election looms.",
  "pubDate": "Mon, 31 Oct 2022 18:20:19 +0000",
  "category": [
    "Trump, Donald J",
    "Trump Tax Returns",
    "Supreme Court (US)",
    "House Committee on Ways and Means",
    "Suits and Litigation (Civil)",
    "Midterm Elections (2022)",
    "United States Politics and Government",
    "McFadden, Trevor N"
  ],
  "media:content": "",
  "media:credit": "Rebecca Noble for The New York Times",
  "media:description": "Lawyers for former President Donald J. Trump asked the Supreme Court to freeze matters while they prepared a formal appeal of a ruling that the House Ways and Means Committee had a right to see his returns."
}