{
  "title": "Can Balenciaga Break With Kanye?",
  "link": "https://www.nytimes.com/2022/10/14/style/kanye-west-balenciaga-demna.html",
  "guid": "https://www.nytimes.com/2022/10/14/style/kanye-west-balenciaga-demna.html",
  "atom:link": "",
  "description": "The fashion brand and the rapper have had an intense love affair. But after Ye’s White Lives Matter shirt and antisemitic comments, the company may need to be heartless.",
  "dc:creator": "Vanessa Friedman",
  "pubDate": "Thu, 20 Oct 2022 03:32:10 +0000",
  "category": [
    "Fashion and Apparel",
    "Paris Fashion Week",
    "Celebrities",
    "Balenciaga (Fashion Label)",
    "Yeezy (Fashion Label)",
    "West, Kanye",
    "Gvasalia, Demna",
    "Anti-Semitism",
    "Race and Ethnicity",
    "Discrimination",
    "your-feed-fashion"
  ],
  "media:content": "",
  "media:credit": "Julien Mignot for The New York Times; Julien De Rosa/Agence France-Presse &mdash; Getty Images"
}