{
  "title": "Brunei Exports",
  "link": "https://tradingeconomics.com/brunei/exports",
  "description": "Exports in Brunei increased to 1433.60 Million BND in July from 1320.70 Million BND in June of 2021. Exports in Brunei averaged 1200.50 Million BND from 2005 until 2021, reaching an all time high of 4137.32 Million BND in September of 2008 and a record low of 491.10 Million BND in August of 2016. Oil and natural gas account for almost 90 percent of Brunei’s exports. Other exports include machinery and transport equipment (5 percent) and chemicals (5 percent). Brunei’s main exports partners are: Japan (35 percent of total imports); South Korea (14 percent); Thailand (9 percent); India (9 percent); Singapore (7 percent); Malaysia (6 percent); China (5 percent); Australia (5 percent) and New Zealand (3 percent).\n\n. This page provides the latest reported value for - Brunei Exports - plus previous releases, historical high and low, short-term forecast and long-term prediction, economic calendar, survey consensus and news.",
  "author": "Department of Economic Planning and Development, Brunei",
  "pubDate": "Wed, 09 Nov 2022 04:39:07 GMT"
}