{
  "title": "Oscar yi Hou’s Paintings Lend New Frames to Queer, Asian Identity",
  "link": "https://www.nytimes.com/2022/10/22/arts/design/oscar-yi-hou-paintings.html",
  "guid": "https://www.nytimes.com/2022/10/22/arts/design/oscar-yi-hou-paintings.html",
  "atom:link": "",
  "description": "The 24-year-old “internet kid” from Liverpool melds contemporary iconography with figurative works of art.",
  "dc:creator": "Ted Loos",
  "pubDate": "Sat, 22 Oct 2022 09:00:11 +0000",
  "category": [
    "Art",
    "yi Hou, Oscar",
    "Brooklyn Museum",
    "Paint",
    "New-York Historical Society",
    "James Fuentes Gallery (Manhattan, NY)",
    "Columbia University"
  ],
  "media:content": "",
  "media:credit": "Vincent Tullo for The New York Times",
  "media:description": "The artist Oscar yi Hou in his studio, with a painting from his Brooklyn show, “Coolieisms, aka: Gold Mountain Cruiser (Mineshaft Trade)” (2022)."
}