{
  "title": "Police Cameras at Pelosi’s House Were Unmonitored as They Caught Break-In",
  "link": "https://www.nytimes.com/2022/11/01/us/politics/pelosi-attack-congress-security-capitol.html",
  "guid": "https://www.nytimes.com/2022/11/01/us/politics/pelosi-attack-congress-security-capitol.html",
  "atom:link": "",
  "description": "Minutes went by before any Capitol Police officer reviewed the footage. Law enforcement leaders said they planned to beef up protections for members of Congress.",
  "pubDate": "Wed, 02 Nov 2022 03:01:47 +0000",
  "category": [
    "United States Politics and Government",
    "Storming of the US Capitol (Jan, 2021)",
    "Assaults",
    "Threats and Threatening Messages",
    "Secret Service",
    "United States Capitol Police",
    "Depape, David",
    "Manger, J Thomas",
    "Pelosi, Nancy",
    "Law and Legislation"
  ],
  "media:content": "",
  "media:credit": "Shuran Huang for The New York Times",
  "media:description": "Many lawmakers say it has long been clear that Capitol security officials must do more to protect them."
}