{
  "title": "Louis Gigante, Priest Who Led South Bronx Revival, Dies at 90",
  "link": "https://www.nytimes.com/2022/10/23/obituaries/louis-gigante-dead.html",
  "guid": "https://www.nytimes.com/2022/10/23/obituaries/louis-gigante-dead.html",
  "atom:link": "",
  "description": "The brother of a convicted Mafia boss, he became a Democratic Party leader and a city councilman, and helped build thousands of units of housing.",
  "dc:creator": "Robert D. McFadden",
  "pubDate": "Sun, 23 Oct 2022 19:19:38 +0000",
  "category": [
    "Deaths (Obituaries)",
    "Priests",
    "Area Planning and Renewal",
    "Gigante, Louis R",
    "Bronx (NYC)",
    "Organized Crime"
  ],
  "media:content": "",
  "media:credit": "Don Hogan Charles/The New York Times",
  "media:description": "The Rev. Louis R. Gigante on a lot in the Bronx. He was instrumental in turning a notorious slum in the South Bronx into a thriving neighborhood."
}