{
  "title": "9/11 Families Protest at Saudi-Backed LIV Golf Tournament",
  "link": "https://www.nytimes.com/2022/07/29/sports/golf/liv-trump-september-11.html",
  "guid": "https://www.nytimes.com/2022/07/29/sports/golf/liv-trump-september-11.html",
  "atom:link": "",
  "description": "The families are furious that former President Donald J. Trump once blamed Saudi Arabia for the terrorist attacks, but is now allowing his golf course to be used for its LIV Golf event.",
  "dc:creator": "David Waldstein",
  "pubDate": "Sat, 30 Jul 2022 03:24:17 +0000",
  "category": [
    "Golf",
    "LIV Golf",
    "Trump National Golf Club (Bedminster, NJ)",
    "September 11 (2001)",
    "Trump, Donald J",
    "World Trade Center (Manhattan, NY)",
    "Mohammed bin Salman (1985- )"
  ],
  "media:content": "",
  "media:credit": "Doug Mills/The New York Times",
  "media:description": "Brett Eagleson, president of 9/11 Justice and the son of John Bruce Eagleson, who died in the South Tower of the World Trade Center, joined other family members of Sept. 11 victims and survivors in a protest of the LIV Golf tournament."
}