{
  "title": "Russia’s Unsupported ‘Dirty Bomb’ Claims Spread Through Right-Wing U.S. Media",
  "link": "https://www.nytimes.com/2022/10/25/technology/dirty-bomb-russia-right-wing-us.html",
  "guid": "https://www.nytimes.com/2022/10/25/technology/dirty-bomb-russia-right-wing-us.html",
  "atom:link": "",
  "description": "Russia’s unsupported claim was portrayed as believable in right-wing American media, and as a warning that could serve to escalate the conflict for Ukraine’s benefit or trigger a world war.",
  "dc:creator": "Stuart A. Thompson",
  "pubDate": "Tue, 25 Oct 2022 19:12:10 +0000",
  "category": [
    "Dirty Bombs and Radiological Weapons",
    "Right-Wing Extremism and Alt-Right",
    "Fringe Groups and Movements",
    "Midterm Elections (2022)",
    "Russian Invasion of Ukraine (2022)",
    "International Relations",
    "Social Media",
    "Infowars",
    "Telegram LLC",
    "Jones, Alex (1974- )"
  ],
  "media:content": "",
  "media:credit": "Russian Defense Ministry Press Service/EPA, via Shutterstock",
  "media:description": "A still image taken from a handout video provided by the Russian Defense Ministry shows Igor Kirillov, the head of Russia’s Radiation, Chemical and Biological Protection Forces, on Monday."
}