{
  "title": "Colts Owner Defends Jeff Saturday’s Hire as Coach",
  "link": "https://www.nytimes.com/2022/11/08/sports/football/jeff-saturday-colts-nfl-coach.html",
  "guid": "https://www.nytimes.com/2022/11/08/sports/football/jeff-saturday-colts-nfl-coach.html",
  "atom:link": "",
  "description": "Jeff Saturday, most recently an ESPN analyst, was tabbed as the team’s interim head coach, having coached only high school football.",
  "dc:creator": "Victor Mather and Emmanuel Morgan",
  "pubDate": "Tue, 08 Nov 2022 22:15:50 +0000",
  "category": [
    "Football",
    "Coaches and Managers",
    "Discrimination",
    "Hiring and Promotion",
    "Indianapolis Colts",
    "National Football League",
    "Flores, Brian (1981- )",
    "Irsay, Jim"
  ],
  "media:content": "",
  "media:credit": "Darron Cummings/Associated Press",
  "media:description": "Jeff Saturday, a former center for the Colts, was named interim coach of the team on Monday. His coaching experience is only at the high school level — at Hebron Christian Academy, a high school in Dacula, Ga., where his record was 20-16."
}