{
  "title": "How to Do a More Conscious Fall Cleanup",
  "link": "https://www.nytimes.com/2022/10/26/realestate/fall-garden-cleanup.html",
  "guid": "https://www.nytimes.com/2022/10/26/realestate/fall-garden-cleanup.html",
  "atom:link": "",
  "description": "Don’t be in a hurry to get rid of all those dead leaves. Autumn is the best time to learn from your garden — if you slow down and pay attention.",
  "dc:creator": "Margaret Roach",
  "pubDate": "Wed, 26 Oct 2022 09:00:48 +0000",
  "category": [
    "Real Estate and Housing (Residential)",
    "Gardens and Gardening",
    "Flowers and Plants",
    "Autumn (Season)",
    "Trees and Shrubs",
    "Content Type: Service",
    "Content Type: Personal Profile",
    "Great Dixter (Northiam, England)",
    "Claverack (NY)"
  ]
}