{
  "title": "Japan 3 Month Bill Yield",
  "link": "https://tradingeconomics.com/japan/3-month-bill-yield",
  "description": "Japan 3 Month Bond Yield was -0.09 percent on Friday November 11, according to over-the-counter interbank yield quotes for this government bond maturity. Historically, the Japan 3 Month Bill Yield reached an all time high of 0.76 in August of 2007. This page includes a chart with historical data for Japan 3M.",
  "author": "",
  "pubDate": "Fri, 11 Nov 2022 00:20:05 GMT"
}