{
  "title": "Tom Brady Has Passed for 100,000 Yards. Sort Of.",
  "link": "https://www.nytimes.com/2022/11/07/sports/football/tom-brady-100000-yards.html",
  "guid": "https://www.nytimes.com/2022/11/07/sports/football/tom-brady-100000-yards.html",
  "atom:link": "",
  "description": "The Buccaneers quarterback reached a career milestone only by adding in his postseason totals to his regular-season mark. But no rival can match him on either list.",
  "dc:creator": "Victor Mather",
  "pubDate": "Mon, 07 Nov 2022 20:58:55 +0000",
  "category": [
    "Playoff Games",
    "Football",
    "Statistics",
    "National Football League",
    "Brady, Tom"
  ],
  "media:content": "",
  "media:credit": "Peter Joneleit/Associated Press",
  "media:description": "Tampa Bay’s stadium announcement of Tom Brady’s milestone came with some fine print."
}