{
  "title": "Stephen Colbert Ponders Dr. Oz’s Views on Abortion",
  "link": "https://www.nytimes.com/2022/10/27/arts/television/stephen-colbert-dr-oz-abortion.html",
  "guid": "https://www.nytimes.com/2022/10/27/arts/television/stephen-colbert-dr-oz-abortion.html",
  "atom:link": "",
  "description": "“No one should have to discuss health care with their local political leaders, especially if you live in one of those really small towns where the local mayor is a dog,” Colbert said.",
  "dc:creator": "Trish Bendix",
  "pubDate": "Thu, 27 Oct 2022 06:50:57 +0000",
  "category": [
    "Television",
    "internal-sub-only",
    "Colbert, Stephen",
    "Kimmel, Jimmy",
    "Noah, Trevor (1984- )",
    "Jimmy Kimmel Live (TV Program)",
    "Late Show with Stephen Colbert (TV Program)",
    "The Tonight Show (TV Program)",
    "Fallon, Jimmy",
    "The Daily Show with Trevor Noah (TV Program)"
  ]
}