{
  "title": "Roger Federer’s Retirement Makes Room for a New Era of Champions",
  "link": "https://www.nytimes.com/2022/09/15/sports/tennis/roger-federer-retires-rafael-nadal-novak-djokovic.html",
  "guid": "https://www.nytimes.com/2022/09/15/sports/tennis/roger-federer-retires-rafael-nadal-novak-djokovic.html",
  "atom:link": "",
  "description": "Roger Federer’s retirement will augur opportunities for a new generation of players not named Rafael Nadal or Novak Djokovic.",
  "dc:creator": "David Waldstein",
  "pubDate": "Fri, 23 Sep 2022 18:13:39 +0000",
  "category": [
    "Tennis",
    "Federer, Roger",
    "Djokovic, Novak",
    "Nadal, Rafael",
    "United States Open (Tennis)",
    "Alcaraz, Carlos (2003- )",
    "Medvedev, Daniil (1996- )",
    "Roddick, Andy"
  ],
  "media:content": "",
  "media:credit": "Asanka Brendon Ratnayake for The New York Times",
  "media:description": "Roger Federer at the Australian Open in 2020."
}