{
  "title": "Tropical Storm Martin to Become a Hurricane on Wednesday",
  "link": "https://www.nytimes.com/article/tropical-storm-martin-hurricane.html",
  "guid": "https://www.nytimes.com/article/tropical-storm-martin-hurricane.html",
  "atom:link": "",
  "description": "Martin became the second named storm to develop in two days, with Tropical Storm Lisa moving west across the western Caribbean.",
  "dc:creator": "The New York Times",
  "pubDate": "Tue, 01 Nov 2022 21:40:47 +0000",
  "category": [
    "Hurricanes and Tropical Storms",
    "Atlantic Ocean",
    "Bermuda"
  ],
  "media:content": "",
  "media:credit": "CIRA/NOAA",
  "media:description": "Tropical Storm Martin, which formed on Tuesday, did not pose an immediate threat to land."
}