{
  "title": "Puerto Rico Coronavirus COVID-19 Deaths",
  "link": "https://tradingeconomics.com/puerto-rico/coronavirus-deaths",
  "description": "Puerto Rico recorded 2 Coronavirus Deaths since the epidemic began, according to the World Health Organization (WHO). In addition, Puerto Rico reported 989932 <b><a href=\"/puerto-rico/coronavirus-cases\">Coronavirus Cases</a></b>. This page includes a chart with historical data for Puerto Rico Coronavirus Deaths.",
  "author": "World Health Organization",
  "pubDate": "Fri, 11 Nov 2022 23:14:42 GMT"
}