{
  "title": "In ‘Tulsa King,’ Sylvester Stallone Tries Something New: Being Himself",
  "link": "https://www.nytimes.com/2022/11/10/arts/television/tulsa-king-sylvester-stallone.html",
  "guid": "https://www.nytimes.com/2022/11/10/arts/television/tulsa-king-sylvester-stallone.html",
  "atom:link": "",
  "description": "His best-known characters often speak in grunts. But in a new series from Taylor Sheridan, he plays a smooth talker written with his real personality in mind.",
  "dc:creator": "Austin Considine",
  "pubDate": "Thu, 10 Nov 2022 17:19:31 +0000",
  "category": [
    "Television",
    "Stallone, Sylvester",
    "Sheridan, Taylor (1970- )",
    "Winter, Terence",
    "Tulsa King (TV Program)"
  ],
  "media:content": "",
  "media:credit": "Sinna Nasseri for The New York Times",
  "media:description": "“I would say at my age, right now, I’m probably doing my best work because I’m actually playing me,” Stallone said."
}