{
  "title": "How Chase Oliver’s Senate Run Helped Lead to a Runoff in Georgia",
  "link": "https://www.nytimes.com/2022/11/09/us/elections/georgia-runoff-chase-oliver.html",
  "guid": "https://www.nytimes.com/2022/11/09/us/elections/georgia-runoff-chase-oliver.html",
  "atom:link": "",
  "description": "Chase Oliver won a little more than 2 percent of the vote. His politics are unusual: He describes himself as “armed and gay.”",
  "dc:creator": "Richard Fausset",
  "pubDate": "Thu, 10 Nov 2022 02:01:54 +0000",
  "category": [
    "Midterm Elections (2022)",
    "Third-Party Politics (US)",
    "Elections, Senate",
    "Democratic Party",
    "Republican Party",
    "Libertarian Party (US)",
    "Senate",
    "Warnock, Raphael G",
    "Walker, Herschel",
    "Oliver, Chase",
    "Georgia"
  ],
  "media:content": {
    "media:credit": "Elijah Nouvelage/Reuters",
    "media:description": "In recent years, a couple of Libertarian Party candidates have had an outsized influence, particularly in elections that have turned on a few percentage points."
  }
}