{
  "title": "Two Right-Wing Operatives Plead Guilty in 2020 Robocall Scheme",
  "link": "https://www.nytimes.com/2022/10/25/us/politics/ohio-robocalls-wohl-burkman-guilty.html",
  "guid": "https://www.nytimes.com/2022/10/25/us/politics/ohio-robocalls-wohl-burkman-guilty.html",
  "atom:link": "",
  "description": "Jacob Wohl and Jack Burkman arranged thousands of robocalls that prosecutors said were intended to discourage residents of minority neighborhoods from voting by mail in 2020.",
  "dc:creator": "Christine Hauser",
  "pubDate": "Tue, 25 Oct 2022 19:07:34 +0000",
  "category": [
    "Right-Wing Extremism and Alt-Right",
    "Midterm Elections (2022)",
    "Voter Fraud (Election Fraud)",
    "Frauds and Swindling",
    "Nessel, Dana",
    "Cuyahoga County (Ohio)"
  ],
  "media:content": "",
  "media:credit": "Joshua Roberts/Reuters",
  "media:description": "Jack Burkman, center, and Jacob Wohl, left, in 2018. Prosecutors said they used robocalls to intimidate residents in minority neighborhoods to refrain from voting by mail in 2020."
}