{
  "title": "Book Review: ‘Saha,’ by Cho Nam-Joo",
  "link": "https://www.nytimes.com/2022/11/01/books/review/saha-cho-nam-joo.html",
  "guid": "https://www.nytimes.com/2022/11/01/books/review/saha-cho-nam-joo.html",
  "atom:link": "",
  "description": "In her new novel, “Saha,” Cho Nam-Joo follows a group of outcasts to examine the strict enforcement of social hierarchies.",
  "dc:creator": "Lincoln Michel",
  "pubDate": "Tue, 01 Nov 2022 09:00:11 +0000",
  "category": [
    "Cho Nam-Joo",
    "Saha (Book)",
    "Books and Literature"
  ],
  "media:content": {
    "media:credit": "Andrea Ucini"
  }
}