{
  "title": "How to Stay Safe During a Crowded Event",
  "link": "https://www.nytimes.com/article/crowd-crush-safety.html",
  "guid": "https://www.nytimes.com/article/crowd-crush-safety.html",
  "atom:link": "",
  "description": "While tragedies such as the deaths of 151 people at a Halloween event in Seoul are rare, anyone attending a big gathering should keep these safety tips in mind, experts say.",
  "dc:creator": "Dani Blum",
  "pubDate": "Mon, 31 Oct 2022 20:24:30 +0000",
  "category": [
    "Stampedes",
    "Content Type: Service",
    "Disasters and Emergencies"
  ],
  "media:content": {
    "media:credit": "Getty Images"
  }
}