{
  "title": "Luxembourg Employment Change",
  "link": "https://tradingeconomics.com/luxembourg/employment-change",
  "description": "Employment in Luxembourg increased by 0.80 in June of 2022. Employment Change in Luxembourg averaged 0.78 percent from 1995 until 2022, reaching an all time high of 1.90 percent in the first quarter of 2001 and a record low of -0.60 percent in the second quarter of 2020. In Luxembourg, employment change refers to the quarterly change in the number of persons who work for pay or profit, or perform unpaid family work. Estimates include both full-time and part-time employment. This page provides - Luxembourg Employment Change- actual values, historical data, forecast, chart, statistics, economic calendar and news.",
  "author": "EUROSTAT",
  "pubDate": "Fri, 11 Nov 2022 02:49:10 GMT"
}