{
  "title": "Arizona Election Officials in Maricopa County: Tone Down the Rhetoric",
  "link": "https://www.nytimes.com/2022/11/10/us/elections/maricopa-arizona-election-gop.html",
  "guid": "https://www.nytimes.com/2022/11/10/us/elections/maricopa-arizona-election-gop.html",
  "atom:link": "",
  "description": "In a news conference, they said they wouldn’t finish counting all the ballots until next week.",
  "dc:creator": "Jim Rutenberg",
  "pubDate": "Fri, 11 Nov 2022 02:49:46 +0000",
  "category": [
    "Midterm Elections (2022)",
    "Lake, Kari A",
    "Maricopa County (Ariz)"
  ],
  "media:content": {
    "media:credit": "Ross D. Franklin/Associated Press",
    "media:description": "Bill Gates, the chairman of the Maricopa Board of Supervisors, on Thursday."
  }
}